Numerical_CFS/Action.py
Numerical_CFS/ActionGraph.py
Numerical_CFS/Diag_Schar.py
Numerical_CFS/FlowChartMaker.py
Numerical_CFS/LibForSimulAnnealing.py
Numerical_CFS/Lib_Action_Minimum.py
Numerical_CFS/PyxPlot3d.py
Numerical_CFS/PyxSchar.py
Numerical_CFS/SymEngineFast.py
Numerical_CFS/Test.py
Numerical_CFS/__init__.py
Numerical_CFS/configfunktion.py
Numerical_CFS/config/Settings.cfg
Numerical_CFS/data/funcprint.c
Numerical_CFS-0.1.9.9.dist-info/DESCRIPTION.rst
Numerical_CFS-0.1.9.9.dist-info/METADATA
Numerical_CFS-0.1.9.9.dist-info/RECORD
Numerical_CFS-0.1.9.9.dist-info/WHEEL
Numerical_CFS-0.1.9.9.dist-info/metadata.json
Numerical_CFS-0.1.9.9.dist-info/top_level.txt
