Metadata-Version: 2.0
Name: Numerical-CFS
Version: 0.1.9.9
Summary: Basically for a set of parameters i use Symengine to produce a function, which is the integrand of the Action-Integral. The integration is done numerically. I am searching for the set of parameters, which minimizes the Integral.
Home-page: UNKNOWN
Author: Mustafa Akman
Author-email: UNKNOWN
License: GPL v3
Platform: UNKNOWN
Requires-Dist: numpy
Requires-Dist: pycallgraph
Requires-Dist: pyx
Requires-Dist: scipy
Requires-Dist: symengine
